vacefron/__init__.py
vacefron/client.py
vacefron/enums.py
vacefron/errors.py
vacefron/http.py
vacefron/utils.py
vacefron/models/__init__.py
vacefron/models/image.py
vacefron/models/rank.py
vacefron/types/http.py
vacefron/types/rank.py
vacefron.py-2.0.3.dist-info/LICENSE
vacefron.py-2.0.3.dist-info/METADATA
vacefron.py-2.0.3.dist-info/WHEEL
vacefron.py-2.0.3.dist-info/top_level.txt
vacefron.py-2.0.3.dist-info/RECORD
