Metadata-Version: 2.1
Name: vacefron.py
Version: 2.0.3
Summary: A Wrapper for vacefron.nl/api written in Python.
Home-page: https://github.com/Soheab/vacefron.py
Download-URL: https://github.com/Soheab/vacefron.py/archive/refs/tags/v2.0.3.tar.gz
Author: Soheab
License: MPL-2.0
Project-URL: Discord, https://discord.gg/xJ2HRxZ
Project-URL: Documentation, https://github.com/Soheab/vacefron.py/blob/master/docs.md
Project-URL: Issue tracker, https://github.com/Soheab/vacefron.py/issues
Keywords: vacefron,discord,api,wrapper,memes,image,discord.py,rankcard,rank,card,aiohttp,leveling
Classifier: Development Status :: 5 - Production/Stable
Classifier: Framework :: aiohttp
Classifier: License :: OSI Approved :: Mozilla Public License 2.0 (MPL 2.0)
Classifier: Natural Language :: English
Classifier: Operating System :: OS Independent
Classifier: Programming Language :: Python :: 3.8
Classifier: Programming Language :: Python :: 3.9
Classifier: Programming Language :: Python :: 3.10
Classifier: Topic :: Internet
Classifier: Topic :: Software Development :: Libraries
Classifier: Topic :: Software Development :: Libraries :: Python Modules
Classifier: Topic :: Utilities
Classifier: Typing :: Typed
Requires-Python: >=3.8
License-File: LICENSE
